bedrock_mcp_proxy/__init__.py
bedrock_mcp_proxy/client.py
bedrock_mcp_proxy/server.py
opsguide_mcp-0.1.4.dist-info/METADATA
opsguide_mcp-0.1.4.dist-info/WHEEL
opsguide_mcp-0.1.4.dist-info/entry_points.txt
opsguide_mcp-0.1.4.dist-info/RECORD
