Metadata-Version: 2.4
Name: opsguide-mcp
Version: 0.1.4
Summary: MCP Server proxy for Amazon Bedrock AgentCore Runtime
Author-email: Ekky Armandi <me@ekky.dev>
License-Expression: MIT
Keywords: ai,bedrock,mcp,opsguide,proxy
Classifier: Development Status :: 4 - Beta
Classifier: Intended Audience :: Developers
Classifier: License :: OSI Approved :: MIT License
Classifier: Programming Language :: Python :: 3
Classifier: Programming Language :: Python :: 3.10
Classifier: Programming Language :: Python :: 3.11
Classifier: Programming Language :: Python :: 3.12
Classifier: Topic :: Software Development :: Libraries :: Python Modules
Requires-Python: >=3.10
Requires-Dist: httpx>=0.24.0
Requires-Dist: mcp>=1.0.0
Requires-Dist: python-dotenv>=1.0.0
